{
	"Menu 201": {
		"Forretter": [
			"Andekød suppe"
		],
		"Mellemretter": [
			"Sprød and med hjemmelavet pandekager"
		],
		"Hovedretter": [
			"stegte kongerejer med krydret salat",
			"stegt peking and med grønsager"
		],
		"price": 188,
		"min_buy": 2
	},
	"Menu 202": {
		"Forretter": [
			"Pekingsuppe"
		],
		"Mellemretter": [
			"Hjemmelavet forårsruller",
			"Kylling og rejer på spyd"
		],
		"Hovedretter": [
			"Oksekød med stærk sauce",
			"Andesteg med bambusskud og champignonsauce"
		],
		"price": 158,
		"min_buy": 2
	}
}